Workbook

Sheet Read me
A1: Azure SQL LTR backups: transfer and long-term storage cost
A3: What this models
B4: The cost of draining Azure SQL Database / Managed Instance long-term retention (LTR) backups into a storage account and keeping them there. Use it when the subscription that owns the LTR backups is going to be deleted.
B5: LTR backups survive deletion of the database, the server and the instance. They do NOT survive deletion of the SUBSCRIPTION. If the subscription can be kept alive, you do not need this pipeline at all, and that is almost always the cheaper answer.
A7: The transfer answer
B8: Transferring the backups into a storage account is FREE in the normal case.
B9: Ingress into Azure Storage is never charged. A subscription boundary is not a billing boundary for network traffic; only a REGION boundary is. So if the destination storage account is in the same region as the source, transfer costs $0 even when it belongs to a completely different subscription or tenant.
B10: You only pay if you cross regions ($0.02/GB) or send the data out to the internet ($0.087/GB). Write operations cost a few cents and are included for completeness.
A12: The real cost
B13: Long-term storage dominates, typically by a factor of 50 or more over everything else. The two levers that matter are the storage TIER and the COMPRESSION RATIO.
A15: How to use it
B16: 1. Open 'Parameters' and set the yellow cells. Everything else recalculates.
B17: 2. 'Cost matrix' sweeps backup count against database size.
B18: 3. 'Tier comparison' shows what each storage tier costs for your scenario, including what it costs to read the data back.
B19: 4. 'Compression sensitivity' shows how much the answer moves with the one number nobody has measured yet.
A21: Confidence
B22: VERIFIED: all prices, taken from the Azure retail prices API (see 'Prices' for the exact retrieval timestamp). Transfer and storage arithmetic.
B23: ASSUMED: the compression ratio. This is the weakest input and it drives the largest term. Measured ratios in testing ranged from 1.02x on incompressible data to 33x on highly repetitive data, against a default assumption of 4x. Budget with the worst ratio you actually observe.
B24: EXCLUDED: the compute cost of restoring each backup before exporting it. It is small and one-time. See Get-LtrExportCostEstimate.ps1 in the toolkit for that half.
A26: Prices retrieved | B26: 2026-09-10T06:32:45.497151+00:00 | region: eastus | USD
A27: Caveat | B27: Retail prices exclude any enterprise agreement discount, reservation or credit.

Sheet Parameters
A1: Parameters (edit the yellow cells)
A3: INPUTS
A4: Number of LTR backups | B4: 60 | C4: How many restore points you must preserve.
A5: Average database size (GB) | B5: 50 | C5: Source size, before compression.
A6: Compression ratio | B6: 4 | C6: Source GB per artifact GB. THE weakest assumption. Measured 1.02x to 33x.
A7: Retention (months) | B7: 84 | C7: 84 = 7 years.
A8: Storage tier | B8: Archive | C8: Hot / Cool / Cold / Archive.
A9: Redundancy | B9: LRS | C9: LRS / ZRS / GRS / GZRS / RA-GRS / RA-GZRS.
A10: Artifact destination | B10: Same region (any subscription) | C10: Same region is free, even across subscriptions.
A11: Upload block size (MB) | B11: 4 | C11: MI BACKUP TO URL uses 4 MB. Only affects the small write-operations term.
A13: RESOLVED RATES
A14: Storage $/GB/month | B14: =IFERROR(INDEX(Prices!$D$5:$D$25,MATCH($B$8&" "&$B$9,Prices!$A$5:$A$25,0)),"not offered") | C14: Looked up from the price snapshot. Archive has no ZRS.
A15: Write $/10k operations | B15: =IFERROR(INDEX(Prices!$E$5:$E$25,MATCH($B$8&" "&$B$9,Prices!$A$5:$A$25,0)),0)
A16: Transfer $/GB | B16: =IFERROR(INDEX(Prices!$B$29:$B$31,MATCH($B$10,Prices!$A$29:$A$31,0)),0) | C16: Egress. Zero unless you cross a region boundary.
A18: VOLUMES
A19: Total source data (GB) | B19: =$B$4*$B$5 | C19: Backups x average size.
A20: Total artifact data (GB) | B20: =IF($B$6>0,$B$19/$B$6,0) | C20: What actually lands in blob storage.
A21: Write operations | B21: =IF($B$11>0,ROUNDUP($B$20*1024/$B$11,0),0) | C21: One block per upload chunk.
A23: COSTS
A24: Transfer: bandwidth | B24: =$B$20*$B$16 | C24: Zero for same-region destinations.
A25: Transfer: write operations | B25: =$B$21/10000*$B$15 | C25: Nearly always trivial.
A26: Transfer: TOTAL (one time) | B26: =$B$24+$B$25 | C26: The whole cost of getting the data in.
A27: Storage per month | B27: =$B$20*$B$14
A28: Storage over full retention | B28: =$B$27*$B$7 | C28: The number that actually matters.
A30: GRAND TOTAL | B30: =$B$26+$B$28 | C30: Transfer plus retention.
A32: Transfer as % of total | B32: =IFERROR($B$26/$B$30,0) | C32: Usually a rounding error next to storage.
A33: Cost to read it all back once | B33: =$B$20*IFERROR(INDEX(Prices!$G$5:$G$25,MATCH($B$8&" "&$B$9,Prices!$A$5:$A$25,0)),0)+$B$21/10000*IFERROR(INDEX(Prices!$F$5:$F$25,MATCH($B$8&" "&$B$9,Prices!$A$5:$A$25,0)),0) | C33: The Archive trap: cheap to keep, not free to retrieve.
A35: Restore/export compute is NOT included here; it is one-time and small. See Get-LtrExportCostEstimate.ps1 for that half of the model.

Sheet Prices
A1: Price snapshot from the Azure retail prices API
A2: Retrieved 2026-09-10T06:32:45.497151+00:00 for region 'eastus' in USD. Product: General Block Blob v2. Data Stored is the first volume band (0-50 TB). Operation meters are not published for every redundancy; missing ones fall back to the LRS rate for the same tier.
A4: Key | B4: Tier | C4: Redundancy | D4: Stored $/GB/month | E4: Write $/10k ops | F4: Read $/10k ops | G4: Retrieval $/GB
A5: Hot GRS | B5: Hot | C5: GRS | D5: 0.0458 | E5: 0.1 | F5: 0.004 | G5: 0
A6: Hot GZRS | B6: Hot | C6: GZRS | D6: 0.0468 | E6: 0.1175 | F6: 0.004 | G6: 0
A7: Hot LRS | B7: Hot | C7: LRS | D7: 0.0208 | E7: 0.05 | F7: 0.004 | G7: 0
A8: Hot RA-GRS | B8: Hot | C8: RA-GRS | D8: 0.0589 | E8: 0.1 | F8: 0.004 | G8: 0
A9: Hot RA-GZRS | B9: Hot | C9: RA-GZRS | D9: 0.0585 | E9: 0.05 | F9: 0.004 | G9: 0
A10: Hot ZRS | B10: Hot | C10: ZRS | D10: 0.026 | E10: 0.0625 | F10: 0.004 | G10: 0
A11: Cool GRS | B11: Cool | C11: GRS | D11: 0.0334 | E11: 0.2 | F11: 0.01 | G11: 0.01
A12: Cool GZRS | B12: Cool | C12: GZRS | D12: 0.0342 | E12: 0.2 | F12: 0.01 | G12: 0.01
A13: Cool LRS | B13: Cool | C13: LRS | D13: 0.0152 | E13: 0.1 | F13: 0.01 | G13: 0.01
A14: Cool RA-GRS | B14: Cool | C14: RA-GRS | D14: 0.0425 | E14: 0.2 | F14: 0.01 | G14: 0.01
A15: Cool RA-GZRS | B15: Cool | C15: RA-GZRS | D15: 0.04275 | E15: 0.1 | F15: 0.01 | G15: 0.01
A16: Cool ZRS | B16: Cool | C16: ZRS | D16: 0.019 | E16: 0.1 | F16: 0.01 | G16: 0.01
... A25: Archive RA-GRS | B25: Archive | C25: RA-GRS | D25: 0.00299 | E25: 0.21 | F25: 5 | G25: 0.02
A27: Bandwidth (egress out of the source region)
A28: Destination | B28: $/GB
A29: Same region (any subscription) | B29: 0
A30: Cross region | B30: 0.02
A31: Out to the internet | B31: 0.087
A33: Ingress into Azure Storage is always free. A subscription boundary costs nothing; only a region boundary does.

Sheet Cost matrix
A1: Cost by number of backups and database size
A2: Uses the compression ratio, retention, tier and destination from 'Parameters'. Rows are backup counts; columns are average database size in GB.
A4: 1. TRANSFER COST (one time) - bandwidth plus write operations
A5: Backups \ Size (GB) | B5: 5 | C5: 10 | D5: 25 | E5: 50 | F5: 100 | G5: 250 | H5: 500 | I5: 1000
A6: 10 | B6: =(10*5/Parameters!$B$6)*Parameters!$B$16+ROUNDUP((10*5/Parameters!$B$6)*1024/Parameters!$B$11,0)/10000*Parameters!$B$15 | C6: =(10*10/Parameters!$B$6)*Parameters!$B$16+ROUNDUP((10*10/Parameters!$B$6)*1024/Parameters!$B$11,0)/10000*Parameters!$B$15 | D6: =(10*25/Parameters!$B$6)*Parameters!$B$16+ROUNDUP((10*25/Parameters!$B$6)*1024/Parameters!$B$11,0)/10000*Parameters!$B$15 | E6: =(10*50/Parameters!$B$6)*Parameters!$B$16+ROUNDUP((10*50/Parameters!$B$6)*1024/Parameters!$B$11,0)/10000*Parameters!$B$15 | F6: =(10*100/Parameters!$B$6)*Parameters!$B$16+ROUNDUP((10*100/Parameters!$B$6)*1024/Parameters!$B$11,0)/10000*Parameters!$B$15 | G6: =(10*250/Parameters!$B$6)*Parameters!$B$16+ROUNDUP((10*250/Parameters!$B$6)*1024/Parameters!$B$11,0)/10000*Parameters!$B$15 | H6: =(10*500/Parameters!$B$6)*Parameters!$B$16+ROUNDUP((10*500/Parameters!$B$6)*1024/Parameters!$B$11,0)/10000*Parameters!$B$15 | I6: =(10*1000/Parameters!$B$6)*Parameters!$B$16+ROUNDUP((10*1000/Parameters!$B$6)*1024/Parameters!$B$11,0)/10000*Parameters!$B$15
A7: 25 | B7: =(25*5/Parameters!$B$6)*Parameters!$B$16+ROUNDUP((25*5/Parameters!$B$6)*1024/Parameters!$B$11,0)/10000*Parameters!$B$15 | C7: =(25*10/Parameters!$B$6)*Parameters!$B$16+ROUNDUP((25*10/Parameters!$B$6)*1024/Parameters!$B$11,0)/10000*Parameters!$B$15 | D7: =(25*25/Parameters!$B$6)*Parameters!$B$16+ROUNDUP((25*25/Parameters!$B$6)*1024/Parameters!$B$11,0)/10000*Parameters!$B$15 | E7: =(25*50/Parameters!$B$6)*Parameters!$B$16+ROUNDUP((25*50/Parameters!$B$6)*1024/Parameters!$B$11,0)/10000*Parameters!$B$15 | F7: =(25*100/Parameters!$B$6)*Parameters!$B$16+ROUNDUP((25*100/Parameters!$B$6)*1024/Parameters!$B$11,0)/10000*Parameters!$B$15 | G7: =(25*250/Parameters!$B$6)*Parameters!$B$16+ROUNDUP((25*250/Parameters!$B$6)*1024/Parameters!$B$11,0)/10000*Parameters!$B$15 | H7: =(25*500/Parameters!$B$6)*Parameters!$B$16+ROUNDUP((25*500/Parameters!$B$6)*1024/Parameters!$B$11,0)/10000*Parameters!$B$15 | I7: =(25*1000/Parameters!$B$6)*Parameters!$B$16+ROUNDUP((25*1000/Parameters!$B$6)*1024/Parameters!$B$11,0)/10000*Parameters!$B$15
A8: 50 | B8: =(50*5/Parameters!$B$6)*Parameters!$B$16+ROUNDUP((50*5/Parameters!$B$6)*1024/Parameters!$B$11,0)/10000*Parameters!$B$15 | C8: =(50*10/Parameters!$B$6)*Parameters!$B$16+ROUNDUP((50*10/Parameters!$B$6)*1024/Parameters!$B$11,0)/10000*Parameters!$B$15 | D8: =(50*25/Parameters!$B$6)*Parameters!$B$16+ROUNDUP((50*25/Parameters!$B$6)*1024/Parameters!$B$11,0)/10000*Parameters!$B$15 | E8: =(50*50/Parameters!$B$6)*Parameters!$B$16+ROUNDUP((50*50/Parameters!$B$6)*1024/Parameters!$B$11,0)/10000*Parameters!$B$15 | F8: =(50*100/Parameters!$B$6)*Parameters!$B$16+ROUNDUP((50*100/Parameters!$B$6)*1024/Parameters!$B$11,0)/10000*Parameters!$B$15 | G8: =(50*250/Parameters!$B$6)*Parameters!$B$16+ROUNDUP((50*250/Parameters!$B$6)*1024/Parameters!$B$11,0)/10000*Parameters!$B$15 | H8: =(50*500/Parameters!$B$6)*Parameters!$B$16+ROUNDUP((50*500/Parameters!$B$6)*1024/Parameters!$B$11,0)/10000*Parameters!$B$15 | I8: =(50*1000/Parameters!$B$6)*Parameters!$B$16+ROUNDUP((50*1000/Parameters!$B$6)*1024/Parameters!$B$11,0)/10000*Parameters!$B$15
A9: 100 | B9: =(100*5/Parameters!$B$6)*Parameters!$B$16+ROUNDUP((100*5/Parameters!$B$6)*1024/Parameters!$B$11,0)/10000*Parameters!$B$15 | C9: =(100*10/Parameters!$B$6)*Parameters!$B$16+ROUNDUP((100*10/Parameters!$B$6)*1024/Parameters!$B$11,0)/10000*Parameters!$B$15 | D9: =(100*25/Parameters!$B$6)*Parameters!$B$16+ROUNDUP((100*25/Parameters!$B$6)*1024/Parameters!$B$11,0)/10000*Parameters!$B$15 | E9: =(100*50/Parameters!$B$6)*Parameters!$B$16+ROUNDUP((100*50/Parameters!$B$6)*1024/Parameters!$B$11,0)/10000*Parameters!$B$15 | F9: =(100*100/Parameters!$B$6)*Parameters!$B$16+ROUNDUP((100*100/Parameters!$B$6)*1024/Parameters!$B$11,0)/10000*Parameters!$B$15 | G9: =(100*250/Parameters!$B$6)*Parameters!$B$16+ROUNDUP((100*250/Parameters!$B$6)*1024/Parameters!$B$11,0)/10000*Parameters!$B$15 | H9: =(100*500/Parameters!$B$6)*Parameters!$B$16+ROUNDUP((100*500/Parameters!$B$6)*1024/Parameters!$B$11,0)/10000*Parameters!$B$15 | I9: =(100*1000/Parameters!$B$6)*Parameters!$B$16+ROUNDUP((100*1000/Parameters!$B$6)*1024/Parameters!$B$11,0)/10000*Parameters!$B$15
A10: 200 | B10: =(200*5/Parameters!$B$6)*Parameters!$B$16+ROUNDUP((200*5/Parameters!$B$6)*1024/Parameters!$B$11,0)/10000*Parameters!$B$15 | C10: =(200*10/Parameters!$B$6)*Parameters!$B$16+ROUNDUP((200*10/Parameters!$B$6)*1024/Parameters!$B$11,0)/10000*Parameters!$B$15 | D10: =(200*25/Parameters!$B$6)*Parameters!$B$16+ROUNDUP((200*25/Parameters!$B$6)*1024/Parameters!$B$11,0)/10000*Parameters!$B$15 | E10: =(200*50/Parameters!$B$6)*Parameters!$B$16+ROUNDUP((200*50/Parameters!$B$6)*1024/Parameters!$B$11,0)/10000*Parameters!$B$15 | F10: =(200*100/Parameters!$B$6)*Parameters!$B$16+ROUNDUP((200*100/Parameters!$B$6)*1024/Parameters!$B$11,0)/10000*Parameters!$B$15 | G10: =(200*250/Parameters!$B$6)*Parameters!$B$16+ROUNDUP((200*250/Parameters!$B$6)*1024/Parameters!$B$11,0)/10000*Parameters!$B$15 | H10: =(200*500/Parameters!$B$6)*Parameters!$B$16+ROUNDUP((200*500/Parameters!$B$6)*1024/Parameters!$B$11,0)/10000*Parameters!$B$15 | I10: =(200*1000/Parameters!$B$6)*Parameters!$B$16+ROUNDUP((200*1000/Parameters!$B$6)*1024/Parameters!$B$11,0)/10000*Parameters!$B$15
A11: 400 | B11: =(400*5/Parameters!$B$6)*Parameters!$B$16+ROUNDUP((400*5/Parameters!$B$6)*1024/Parameters!$B$11,0)/10000*Parameters!$B$15 | C11: =(400*10/Parameters!$B$6)*Parameters!$B$16+ROUNDUP((400*10/Parameters!$B$6)*1024/Parameters!$B$11,0)/10000*Parameters!$B$15 | D11: =(400*25/Parameters!$B$6)*Parameters!$B$16+ROUNDUP((400*25/Parameters!$B$6)*1024/Parameters!$B$11,0)/10000*Parameters!$B$15 | E11: =(400*50/Parameters!$B$6)*Parameters!$B$16+ROUNDUP((400*50/Parameters!$B$6)*1024/Parameters!$B$11,0)/10000*Parameters!$B$15 | F11: =(400*100/Parameters!$B$6)*Parameters!$B$16+ROUNDUP((400*100/Parameters!$B$6)*1024/Parameters!$B$11,0)/10000*Parameters!$B$15 | G11: =(400*250/Parameters!$B$6)*Parameters!$B$16+ROUNDUP((400*250/Parameters!$B$6)*1024/Parameters!$B$11,0)/10000*Parameters!$B$15 | H11: =(400*500/Parameters!$B$6)*Parameters!$B$16+ROUNDUP((400*500/Parameters!$B$6)*1024/Parameters!$B$11,0)/10000*Parameters!$B$15 | I11: =(400*1000/Parameters!$B$6)*Parameters!$B$16+ROUNDUP((400*1000/Parameters!$B$6)*1024/Parameters!$B$11,0)/10000*Parameters!$B$15
A12: 800 | B12: =(800*5/Parameters!$B$6)*Parameters!$B$16+ROUNDUP((800*5/Parameters!$B$6)*1024/Parameters!$B$11,0)/10000*Parameters!$B$15 | C12: =(800*10/Parameters!$B$6)*Parameters!$B$16+ROUNDUP((800*10/Parameters!$B$6)*1024/Parameters!$B$11,0)/10000*Parameters!$B$15 | D12: =(800*25/Parameters!$B$6)*Parameters!$B$16+ROUNDUP((800*25/Parameters!$B$6)*1024/Parameters!$B$11,0)/10000*Parameters!$B$15 | E12: =(800*50/Parameters!$B$6)*Parameters!$B$16+ROUNDUP((800*50/Parameters!$B$6)*1024/Parameters!$B$11,0)/10000*Parameters!$B$15 | F12: =(800*100/Parameters!$B$6)*Parameters!$B$16+ROUNDUP((800*100/Parameters!$B$6)*1024/Parameters!$B$11,0)/10000*Parameters!$B$15 | G12: =(800*250/Parameters!$B$6)*Parameters!$B$16+ROUNDUP((800*250/Parameters!$B$6)*1024/Parameters!$B$11,0)/10000*Parameters!$B$15 | H12: =(800*500/Parameters!$B$6)*Parameters!$B$16+ROUNDUP((800*500/Parameters!$B$6)*1024/Parameters!$B$11,0)/10000*Parameters!$B$15 | I12: =(800*1000/Parameters!$B$6)*Parameters!$B$16+ROUNDUP((800*1000/Parameters!$B$6)*1024/Parameters!$B$11,0)/10000*Parameters!$B$15
A15: 2. STORAGE COST over the full retention period
A16: Backups \ Size (GB) | B16: 5 | C16: 10 | D16: 25 | E16: 50 | F16: 100 | G16: 250 | H16: 500 | I16: 1000
A17: 10 | B17: =(10*5/Parameters!$B$6)*Parameters!$B$14*Parameters!$B$7 | C17: =(10*10/Parameters!$B$6)*Parameters!$B$14*Parameters!$B$7 | D17: =(10*25/Parameters!$B$6)*Parameters!$B$14*Parameters!$B$7 | E17: =(10*50/Parameters!$B$6)*Parameters!$B$14*Parameters!$B$7 | F17: =(10*100/Parameters!$B$6)*Parameters!$B$14*Parameters!$B$7 | G17: =(10*250/Parameters!$B$6)*Parameters!$B$14*Parameters!$B$7 | H17: =(10*500/Parameters!$B$6)*Parameters!$B$14*Parameters!$B$7 | I17: =(10*1000/Parameters!$B$6)*Parameters!$B$14*Parameters!$B$7
A18: 25 | B18: =(25*5/Parameters!$B$6)*Parameters!$B$14*Parameters!$B$7 | C18: =(25*10/Parameters!$B$6)*Parameters!$B$14*Parameters!$B$7 | D18: =(25*25/Parameters!$B$6)*Parameters!$B$14*Parameters!$B$7 | E18: =(25*50/Parameters!$B$6)*Parameters!$B$14*Parameters!$B$7 | F18: =(25*100/Parameters!$B$6)*Parameters!$B$14*Parameters!$B$7 | G18: =(25*250/Parameters!$B$6)*Parameters!$B$14*Parameters!$B$7 | H18: =(25*500/Parameters!$B$6)*Parameters!$B$14*Parameters!$B$7 | I18: =(25*1000/Parameters!$B$6)*Parameters!$B$14*Parameters!$B$7
A19: 50 | B19: =(50*5/Parameters!$B$6)*Parameters!$B$14*Parameters!$B$7 | C19: =(50*10/Parameters!$B$6)*Parameters!$B$14*Parameters!$B$7 | D19: =(50*25/Parameters!$B$6)*Parameters!$B$14*Parameters!$B$7 | E19: =(50*50/Parameters!$B$6)*Parameters!$B$14*Parameters!$B$7 | F19: =(50*100/Parameters!$B$6)*Parameters!$B$14*Parameters!$B$7 | G19: =(50*250/Parameters!$B$6)*Parameters!$B$14*Parameters!$B$7 | H19: =(50*500/Parameters!$B$6)*Parameters!$B$14*Parameters!$B$7 | I19: =(50*1000/Parameters!$B$6)*Parameters!$B$14*Parameters!$B$7
A20: 100 | B20: =(100*5/Parameters!$B$6)*Parameters!$B$14*Parameters!$B$7 | C20: =(100*10/Parameters!$B$6)*Parameters!$B$14*Parameters!$B$7 | D20: =(100*25/Parameters!$B$6)*Parameters!$B$14*Parameters!$B$7 | E20: =(100*50/Parameters!$B$6)*Parameters!$B$14*Parameters!$B$7 | F20: =(100*100/Parameters!$B$6)*Parameters!$B$14*Parameters!$B$7 | G20: =(100*250/Parameters!$B$6)*Parameters!$B$14*Parameters!$B$7 | H20: =(100*500/Parameters!$B$6)*Parameters!$B$14*Parameters!$B$7 | I20: =(100*1000/Parameters!$B$6)*Parameters!$B$14*Parameters!$B$7
A21: 200 | B21: =(200*5/Parameters!$B$6)*Parameters!$B$14*Parameters!$B$7 | C21: =(200*10/Parameters!$B$6)*Parameters!$B$14*Parameters!$B$7 | D21: =(200*25/Parameters!$B$6)*Parameters!$B$14*Parameters!$B$7 | E21: =(200*50/Parameters!$B$6)*Parameters!$B$14*Parameters!$B$7 | F21: =(200*100/Parameters!$B$6)*Parameters!$B$14*Parameters!$B$7 | G21: =(200*250/Parameters!$B$6)*Parameters!$B$14*Parameters!$B$7 | H21: =(200*500/Parameters!$B$6)*Parameters!$B$14*Parameters!$B$7 | I21: =(200*1000/Parameters!$B$6)*Parameters!$B$14*Parameters!$B$7
A22: 400 | B22: =(400*5/Parameters!$B$6)*Parameters!$B$14*Parameters!$B$7 | C22: =(400*10/Parameters!$B$6)*Parameters!$B$14*Parameters!$B$7 | D22: =(400*25/Parameters!$B$6)*Parameters!$B$14*Parameters!$B$7 | E22: =(400*50/Parameters!$B$6)*Parameters!$B$14*Parameters!$B$7 | F22: =(400*100/Parameters!$B$6)*Parameters!$B$14*Parameters!$B$7 | G22: =(400*250/Parameters!$B$6)*Parameters!$B$14*Parameters!$B$7 | H22: =(400*500/Parameters!$B$6)*Parameters!$B$14*Parameters!$B$7 | I22: =(400*1000/Parameters!$B$6)*Parameters!$B$14*Parameters!$B$7
A23: 800 | B23: =(800*5/Parameters!$B$6)*Parameters!$B$14*Parameters!$B$7 | C23: =(800*10/Parameters!$B$6)*Parameters!$B$14*Parameters!$B$7 | D23: =(800*25/Parameters!$B$6)*Parameters!$B$14*Parameters!$B$7 | E23: =(800*50/Parameters!$B$6)*Parameters!$B$14*Parameters!$B$7 | F23: =(800*100/Parameters!$B$6)*Parameters!$B$14*Parameters!$B$7 | G23: =(800*250/Parameters!$B$6)*Parameters!$B$14*Parameters!$B$7 | H23: =(800*500/Parameters!$B$6)*Parameters!$B$14*Parameters!$B$7 | I23: =(800*1000/Parameters!$B$6)*Parameters!$B$14*Parameters!$B$7
A26: 3. TOTAL - transfer plus storage
A27: Backups \ Size (GB) | B27: 5 | C27: 10 | D27: 25 | E27: 50 | F27: 100 | G27: 250 | H27: 500 | I27: 1000
A28: 10 | B28: =(10*5/Parameters!$B$6)*Parameters!$B$16+ROUNDUP((10*5/Parameters!$B$6)*1024/Parameters!$B$11,0)/10000*Parameters!$B$15+(10*5/Parameters!$B$6)*Parameters!$B$14*Parameters!$B$7 | C28: =(10*10/Parameters!$B$6)*Parameters!$B$16+ROUNDUP((10*10/Parameters!$B$6)*1024/Parameters!$B$11,0)/10000*Parameters!$B$15+(10*10/Parameters!$B$6)*Parameters!$B$14*Parameters!$B$7 | D28: =(10*25/Parameters!$B$6)*Parameters!$B$16+ROUNDUP((10*25/Parameters!$B$6)*1024/Parameters!$B$11,0)/10000*Parameters!$B$15+(10*25/Parameters!$B$6)*Parameters!$B$14*Parameters!$B$7 | E28: =(10*50/Parameters!$B$6)*Parameters!$B$16+ROUNDUP((10*50/Parameters!$B$6)*1024/Parameters!$B$11,0)/10000*Parameters!$B$15+(10*50/Parameters!$B$6)*Parameters!$B$14*Parameters!$B$7 | F28: =(10*100/Parameters!$B$6)*Parameters!$B$16+ROUNDUP((10*100/Parameters!$B$6)*1024/Parameters!$B$11,0)/10000*Parameters!$B$15+(10*100/Parameters!$B$6)*Parameters!$B$14*Parameters!$B$7 | G28: =(10*250/Parameters!$B$6)*Parameters!$B$16+ROUNDUP((10*250/Parameters!$B$6)*1024/Parameters!$B$11,0)/10000*Parameters!$B$15+(10*250/Parameters!$B$6)*Parameters!$B$14*Parameters!$B$7 | H28: =(10*500/Parameters!$B$6)*Parameters!$B$16+ROUNDUP((10*500/Parameters!$B$6)*1024/Parameters!$B$11,0)/10000*Parameters!$B$15+(10*500/Parameters!$B$6)*Parameters!$B$14*Parameters!$B$7 | I28: =(10*1000/Parameters!$B$6)*Parameters!$B$16+ROUNDUP((10*1000/Parameters!$B$6)*1024/Parameters!$B$11,0)/10000*Parameters!$B$15+(10*1000/Parameters!$B$6)*Parameters!$B$14*Parameters!$B$7
A29: 25 | B29: =(25*5/Parameters!$B$6)*Parameters!$B$16+ROUNDUP((25*5/Parameters!$B$6)*1024/Parameters!$B$11,0)/10000*Parameters!$B$15+(25*5/Parameters!$B$6)*Parameters!$B$14*Parameters!$B$7 | C29: =(25*10/Parameters!$B$6)*Parameters!$B$16+ROUNDUP((25*10/Parameters!$B$6)*1024/Parameters!$B$11,0)/10000*Parameters!$B$15+(25*10/Parameters!$B$6)*Parameters!$B$14*Parameters!$B$7 | D29: =(25*25/Parameters!$B$6)*Parameters!$B$16+ROUNDUP((25*25/Parameters!$B$6)*1024/Parameters!$B$11,0)/10000*Parameters!$B$15+(25*25/Parameters!$B$6)*Parameters!$B$14*Parameters!$B$7 | E29: =(25*50/Parameters!$B$6)*Parameters!$B$16+ROUNDUP((25*50/Parameters!$B$6)*1024/Parameters!$B$11,0)/10000*Parameters!$B$15+(25*50/Parameters!$B$6)*Parameters!$B$14*Parameters!$B$7 | F29: =(25*100/Parameters!$B$6)*Parameters!$B$16+ROUNDUP((25*100/Parameters!$B$6)*1024/Parameters!$B$11,0)/10000*Parameters!$B$15+(25*100/Parameters!$B$6)*Parameters!$B$14*Parameters!$B$7 | G29: =(25*250/Parameters!$B$6)*Parameters!$B$16+ROUNDUP((25*250/Parameters!$B$6)*1024/Parameters!$B$11,0)/10000*Parameters!$B$15+(25*250/Parameters!$B$6)*Parameters!$B$14*Parameters!$B$7 | H29: =(25*500/Parameters!$B$6)*Parameters!$B$16+ROUNDUP((25*500/Parameters!$B$6)*1024/Parameters!$B$11,0)/10000*Parameters!$B$15+(25*500/Parameters!$B$6)*Parameters!$B$14*Parameters!$B$7 | I29: =(25*1000/Parameters!$B$6)*Parameters!$B$16+ROUNDUP((25*1000/Parameters!$B$6)*1024/Parameters!$B$11,0)/10000*Parameters!$B$15+(25*1000/Parameters!$B$6)*Parameters!$B$14*Parameters!$B$7
A30: 50 | B30: =(50*5/Parameters!$B$6)*Parameters!$B$16+ROUNDUP((50*5/Parameters!$B$6)*1024/Parameters!$B$11,0)/10000*Parameters!$B$15+(50*5/Parameters!$B$6)*Parameters!$B$14*Parameters!$B$7 | C30: =(50*10/Parameters!$B$6)*Parameters!$B$16+ROUNDUP((50*10/Parameters!$B$6)*1024/Parameters!$B$11,0)/10000*Parameters!$B$15+(50*10/Parameters!$B$6)*Parameters!$B$14*Parameters!$B$7 | D30: =(50*25/Parameters!$B$6)*Parameters!$B$16+ROUNDUP((50*25/Parameters!$B$6)*1024/Parameters!$B$11,0)/10000*Parameters!$B$15+(50*25/Parameters!$B$6)*Parameters!$B$14*Parameters!$B$7 | E30: =(50*50/Parameters!$B$6)*Parameters!$B$16+ROUNDUP((50*50/Parameters!$B$6)*1024/Parameters!$B$11,0)/10000*Parameters!$B$15+(50*50/Parameters!$B$6)*Parameters!$B$14*Parameters!$B$7 | F30: =(50*100/Parameters!$B$6)*Parameters!$B$16+ROUNDUP((50*100/Parameters!$B$6)*1024/Parameters!$B$11,0)/10000*Parameters!$B$15+(50*100/Parameters!$B$6)*Parameters!$B$14*Parameters!$B$7 | G30: =(50*250/Parameters!$B$6)*Parameters!$B$16+ROUNDUP((50*250/Parameters!$B$6)*1024/Parameters!$B$11,0)/10000*Parameters!$B$15+(50*250/Parameters!$B$6)*Parameters!$B$14*Parameters!$B$7 | H30: =(50*500/Parameters!$B$6)*Parameters!$B$16+ROUNDUP((50*500/Parameters!$B$6)*1024/Parameters!$B$11,0)/10000*Parameters!$B$15+(50*500/Parameters!$B$6)*Parameters!$B$14*Parameters!$B$7 | I30: =(50*1000/Parameters!$B$6)*Parameters!$B$16+ROUNDUP((50*1000/Parameters!$B$6)*1024/Parameters!$B$11,0)/10000*Parameters!$B$15+(50*1000/Parameters!$B$6)*Parameters!$B$14*Parameters!$B$7
A31: 100 | B31: =(100*5/Parameters!$B$6)*Parameters!$B$16+ROUNDUP((100*5/Parameters!$B$6)*1024/Parameters!$B$11,0)/10000*Parameters!$B$15+(100*5/Parameters!$B$6)*Parameters!$B$14*Parameters!$B$7 | C31: =(100*10/Parameters!$B$6)*Parameters!$B$16+ROUNDUP((100*10/Parameters!$B$6)*1024/Parameters!$B$11,0)/10000*Parameters!$B$15+(100*10/Parameters!$B$6)*Parameters!$B$14*Parameters!$B$7 | D31: =(100*25/Parameters!$B$6)*Parameters!$B$16+ROUNDUP((100*25/Parameters!$B$6)*1024/Parameters!$B$11,0)/10000*Parameters!$B$15+(100*25/Parameters!$B$6)*Parameters!$B$14*Parameters!$B$7 | E31: =(100*50/Parameters!$B$6)*Parameters!$B$16+ROUNDUP((100*50/Parameters!$B$6)*1024/Parameters!$B$11,0)/10000*Parameters!$B$15+(100*50/Parameters!$B$6)*Parameters!$B$14*Parameters!$B$7 | F31: =(100*100/Parameters!$B$6)*Parameters!$B$16+ROUNDUP((100*100/Parameters!$B$6)*1024/Parameters!$B$11,0)/10000*Parameters!$B$15+(100*100/Parameters!$B$6)*Parameters!$B$14*Parameters!$B$7 | G31: =(100*250/Parameters!$B$6)*Parameters!$B$16+ROUNDUP((100*250/Parameters!$B$6)*1024/Parameters!$B$11,0)/10000*Parameters!$B$15+(100*250/Parameters!$B$6)*Parameters!$B$14*Parameters!$B$7 | H31: =(100*500/Parameters!$B$6)*Parameters!$B$16+ROUNDUP((100*500/Parameters!$B$6)*1024/Parameters!$B$11,0)/10000*Parameters!$B$15+(100*500/Parameters!$B$6)*Parameters!$B$14*Parameters!$B$7 | I31: =(100*1000/Parameters!$B$6)*Parameters!$B$16+ROUNDUP((100*1000/Parameters!$B$6)*1024/Parameters!$B$11,0)/10000*Parameters!$B$15+(100*1000/Parameters!$B$6)*Parameters!$B$14*Parameters!$B$7
A32: 200 | B32: =(200*5/Parameters!$B$6)*Parameters!$B$16+ROUNDUP((200*5/Parameters!$B$6)*1024/Parameters!$B$11,0)/10000*Parameters!$B$15+(200*5/Parameters!$B$6)*Parameters!$B$14*Parameters!$B$7 | C32: =(200*10/Parameters!$B$6)*Parameters!$B$16+ROUNDUP((200*10/Parameters!$B$6)*1024/Parameters!$B$11,0)/10000*Parameters!$B$15+(200*10/Parameters!$B$6)*Parameters!$B$14*Parameters!$B$7 | D32: =(200*25/Parameters!$B$6)*Parameters!$B$16+ROUNDUP((200*25/Parameters!$B$6)*1024/Parameters!$B$11,0)/10000*Parameters!$B$15+(200*25/Parameters!$B$6)*Parameters!$B$14*Parameters!$B$7 | E32: =(200*50/Parameters!$B$6)*Parameters!$B$16+ROUNDUP((200*50/Parameters!$B$6)*1024/Parameters!$B$11,0)/10000*Parameters!$B$15+(200*50/Parameters!$B$6)*Parameters!$B$14*Parameters!$B$7 | F32: =(200*100/Parameters!$B$6)*Parameters!$B$16+ROUNDUP((200*100/Parameters!$B$6)*1024/Parameters!$B$11,0)/10000*Parameters!$B$15+(200*100/Parameters!$B$6)*Parameters!$B$14*Parameters!$B$7 | G32: =(200*250/Parameters!$B$6)*Parameters!$B$16+ROUNDUP((200*250/Parameters!$B$6)*1024/Parameters!$B$11,0)/10000*Parameters!$B$15+(200*250/Parameters!$B$6)*Parameters!$B$14*Parameters!$B$7 | H32: =(200*500/Parameters!$B$6)*Parameters!$B$16+ROUNDUP((200*500/Parameters!$B$6)*1024/Parameters!$B$11,0)/10000*Parameters!$B$15+(200*500/Parameters!$B$6)*Parameters!$B$14*Parameters!$B$7 | I32: =(200*1000/Parameters!$B$6)*Parameters!$B$16+ROUNDUP((200*1000/Parameters!$B$6)*1024/Parameters!$B$11,0)/10000*Parameters!$B$15+(200*1000/Parameters!$B$6)*Parameters!$B$14*Parameters!$B$7
A33: 400 | B33: =(400*5/Parameters!$B$6)*Parameters!$B$16+ROUNDUP((400*5/Parameters!$B$6)*1024/Parameters!$B$11,0)/10000*Parameters!$B$15+(400*5/Parameters!$B$6)*Parameters!$B$14*Parameters!$B$7 | C33: =(400*10/Parameters!$B$6)*Parameters!$B$16+ROUNDUP((400*10/Parameters!$B$6)*1024/Parameters!$B$11,0)/10000*Parameters!$B$15+(400*10/Parameters!$B$6)*Parameters!$B$14*Parameters!$B$7 | D33: =(400*25/Parameters!$B$6)*Parameters!$B$16+ROUNDUP((400*25/Parameters!$B$6)*1024/Parameters!$B$11,0)/10000*Parameters!$B$15+(400*25/Parameters!$B$6)*Parameters!$B$14*Parameters!$B$7 | E33: =(400*50/Parameters!$B$6)*Parameters!$B$16+ROUNDUP((400*50/Parameters!$B$6)*1024/Parameters!$B$11,0)/10000*Parameters!$B$15+(400*50/Parameters!$B$6)*Parameters!$B$14*Parameters!$B$7 | F33: =(400*100/Parameters!$B$6)*Parameters!$B$16+ROUNDUP((400*100/Parameters!$B$6)*1024/Parameters!$B$11,0)/10000*Parameters!$B$15+(400*100/Parameters!$B$6)*Parameters!$B$14*Parameters!$B$7 | G33: =(400*250/Parameters!$B$6)*Parameters!$B$16+ROUNDUP((400*250/Parameters!$B$6)*1024/Parameters!$B$11,0)/10000*Parameters!$B$15+(400*250/Parameters!$B$6)*Parameters!$B$14*Parameters!$B$7 | H33: =(400*500/Parameters!$B$6)*Parameters!$B$16+ROUNDUP((400*500/Parameters!$B$6)*1024/Parameters!$B$11,0)/10000*Parameters!$B$15+(400*500/Parameters!$B$6)*Parameters!$B$14*Parameters!$B$7 | I33: =(400*1000/Parameters!$B$6)*Parameters!$B$16+ROUNDUP((400*1000/Parameters!$B$6)*1024/Parameters!$B$11,0)/10000*Parameters!$B$15+(400*1000/Parameters!$B$6)*Parameters!$B$14*Parameters!$B$7
A34: 800 | B34: =(800*5/Parameters!$B$6)*Parameters!$B$16+ROUNDUP((800*5/Parameters!$B$6)*1024/Parameters!$B$11,0)/10000*Parameters!$B$15+(800*5/Parameters!$B$6)*Parameters!$B$14*Parameters!$B$7 | C34: =(800*10/Parameters!$B$6)*Parameters!$B$16+ROUNDUP((800*10/Parameters!$B$6)*1024/Parameters!$B$11,0)/10000*Parameters!$B$15+(800*10/Parameters!$B$6)*Parameters!$B$14*Parameters!$B$7 | D34: =(800*25/Parameters!$B$6)*Parameters!$B$16+ROUNDUP((800*25/Parameters!$B$6)*1024/Parameters!$B$11,0)/10000*Parameters!$B$15+(800*25/Parameters!$B$6)*Parameters!$B$14*Parameters!$B$7 | E34: =(800*50/Parameters!$B$6)*Parameters!$B$16+ROUNDUP((800*50/Parameters!$B$6)*1024/Parameters!$B$11,0)/10000*Parameters!$B$15+(800*50/Parameters!$B$6)*Parameters!$B$14*Parameters!$B$7 | F34: =(800*100/Parameters!$B$6)*Parameters!$B$16+ROUNDUP((800*100/Parameters!$B$6)*1024/Parameters!$B$11,0)/10000*Parameters!$B$15+(800*100/Parameters!$B$6)*Parameters!$B$14*Parameters!$B$7 | G34: =(800*250/Parameters!$B$6)*Parameters!$B$16+ROUNDUP((800*250/Parameters!$B$6)*1024/Parameters!$B$11,0)/10000*Parameters!$B$15+(800*250/Parameters!$B$6)*Parameters!$B$14*Parameters!$B$7 | H34: =(800*500/Parameters!$B$6)*Parameters!$B$16+ROUNDUP((800*500/Parameters!$B$6)*1024/Parameters!$B$11,0)/10000*Parameters!$B$15+(800*500/Parameters!$B$6)*Parameters!$B$14*Parameters!$B$7 | I34: =(800*1000/Parameters!$B$6)*Parameters!$B$16+ROUNDUP((800*1000/Parameters!$B$6)*1024/Parameters!$B$11,0)/10000*Parameters!$B$15+(800*1000/Parameters!$B$6)*Parameters!$B$14*Parameters!$B$7
A37: If block 1 is all zeros, that is correct: same-region transfer is free, including into a storage account in a different subscription.

Sheet Tier comparison
A1: What each storage tier costs for the current scenario
A2: Scenario comes from 'Parameters'. 'Read back once' is what it costs to retrieve every artifact a single time: the column people forget until an auditor asks.
A4: Tier + redundancy | B4: Stored $/GB/mo | C4: Storage / month | D4: Storage over retention | E4: Transfer (one time) | F4: TOTAL | G4: Read back once
A5: Hot GRS | B5: =INDEX(Prices!$D$5:$D$25,MATCH("Hot GRS",Prices!$A$5:$A$25,0)) | C5: =Parameters!$B$20*$B5 | D5: =$C5*Parameters!$B$7 | E5: =Parameters!$B$20*Parameters!$B$16+Parameters!$B$21/10000*INDEX(Prices!$E$5:$E$25,MATCH("Hot GRS",Prices!$A$5:$A$25,0)) | F5: =$D5+$E5 | G5: =Parameters!$B$20*INDEX(Prices!$G$5:$G$25,MATCH("Hot GRS",Prices!$A$5:$A$25,0))+Parameters!$B$21/10000*INDEX(Prices!$F$5:$F$25,MATCH("Hot GRS",Prices!$A$5:$A$25,0))
A6: Hot GZRS | B6: =INDEX(Prices!$D$5:$D$25,MATCH("Hot GZRS",Prices!$A$5:$A$25,0)) | C6: =Parameters!$B$20*$B6 | D6: =$C6*Parameters!$B$7 | E6: =Parameters!$B$20*Parameters!$B$16+Parameters!$B$21/10000*INDEX(Prices!$E$5:$E$25,MATCH("Hot GZRS",Prices!$A$5:$A$25,0)) | F6: =$D6+$E6 | G6: =Parameters!$B$20*INDEX(Prices!$G$5:$G$25,MATCH("Hot GZRS",Prices!$A$5:$A$25,0))+Parameters!$B$21/10000*INDEX(Prices!$F$5:$F$25,MATCH("Hot GZRS",Prices!$A$5:$A$25,0))
A7: Hot LRS | B7: =INDEX(Prices!$D$5:$D$25,MATCH("Hot LRS",Prices!$A$5:$A$25,0)) | C7: =Parameters!$B$20*$B7 | D7: =$C7*Parameters!$B$7 | E7: =Parameters!$B$20*Parameters!$B$16+Parameters!$B$21/10000*INDEX(Prices!$E$5:$E$25,MATCH("Hot LRS",Prices!$A$5:$A$25,0)) | F7: =$D7+$E7 | G7: =Parameters!$B$20*INDEX(Prices!$G$5:$G$25,MATCH("Hot LRS",Prices!$A$5:$A$25,0))+Parameters!$B$21/10000*INDEX(Prices!$F$5:$F$25,MATCH("Hot LRS",Prices!$A$5:$A$25,0))
A8: Hot RA-GRS | B8: =INDEX(Prices!$D$5:$D$25,MATCH("Hot RA-GRS",Prices!$A$5:$A$25,0)) | C8: =Parameters!$B$20*$B8 | D8: =$C8*Parameters!$B$7 | E8: =Parameters!$B$20*Parameters!$B$16+Parameters!$B$21/10000*INDEX(Prices!$E$5:$E$25,MATCH("Hot RA-GRS",Prices!$A$5:$A$25,0)) | F8: =$D8+$E8 | G8: =Parameters!$B$20*INDEX(Prices!$G$5:$G$25,MATCH("Hot RA-GRS",Prices!$A$5:$A$25,0))+Parameters!$B$21/10000*INDEX(Prices!$F$5:$F$25,MATCH("Hot RA-GRS",Prices!$A$5:$A$25,0))
A9: Hot RA-GZRS | B9: =INDEX(Prices!$D$5:$D$25,MATCH("Hot RA-GZRS",Prices!$A$5:$A$25,0)) | C9: =Parameters!$B$20*$B9 | D9: =$C9*Parameters!$B$7 | E9: =Parameters!$B$20*Parameters!$B$16+Parameters!$B$21/10000*INDEX(Prices!$E$5:$E$25,MATCH("Hot RA-GZRS",Prices!$A$5:$A$25,0)) | F9: =$D9+$E9 | G9: =Parameters!$B$20*INDEX(Prices!$G$5:$G$25,MATCH("Hot RA-GZRS",Prices!$A$5:$A$25,0))+Parameters!$B$21/10000*INDEX(Prices!$F$5:$F$25,MATCH("Hot RA-GZRS",Prices!$A$5:$A$25,0))
A10: Hot ZRS | B10: =INDEX(Prices!$D$5:$D$25,MATCH("Hot ZRS",Prices!$A$5:$A$25,0)) | C10: =Parameters!$B$20*$B10 | D10: =$C10*Parameters!$B$7 | E10: =Parameters!$B$20*Parameters!$B$16+Parameters!$B$21/10000*INDEX(Prices!$E$5:$E$25,MATCH("Hot ZRS",Prices!$A$5:$A$25,0)) | F10: =$D10+$E10 | G10: =Parameters!$B$20*INDEX(Prices!$G$5:$G$25,MATCH("Hot ZRS",Prices!$A$5:$A$25,0))+Parameters!$B$21/10000*INDEX(Prices!$F$5:$F$25,MATCH("Hot ZRS",Prices!$A$5:$A$25,0))
A11: Cool GRS | B11: =INDEX(Prices!$D$5:$D$25,MATCH("Cool GRS",Prices!$A$5:$A$25,0)) | C11: =Parameters!$B$20*$B11 | D11: =$C11*Parameters!$B$7 | E11: =Parameters!$B$20*Parameters!$B$16+Parameters!$B$21/10000*INDEX(Prices!$E$5:$E$25,MATCH("Cool GRS",Prices!$A$5:$A$25,0)) | F11: =$D11+$E11 | G11: =Parameters!$B$20*INDEX(Prices!$G$5:$G$25,MATCH("Cool GRS",Prices!$A$5:$A$25,0))+Parameters!$B$21/10000*INDEX(Prices!$F$5:$F$25,MATCH("Cool GRS",Prices!$A$5:$A$25,0))
A12: Cool GZRS | B12: =INDEX(Prices!$D$5:$D$25,MATCH("Cool GZRS",Prices!$A$5:$A$25,0)) | C12: =Parameters!$B$20*$B12 | D12: =$C12*Parameters!$B$7 | E12: =Parameters!$B$20*Parameters!$B$16+Parameters!$B$21/10000*INDEX(Prices!$E$5:$E$25,MATCH("Cool GZRS",Prices!$A$5:$A$25,0)) | F12: =$D12+$E12 | G12: =Parameters!$B$20*INDEX(Prices!$G$5:$G$25,MATCH("Cool GZRS",Prices!$A$5:$A$25,0))+Parameters!$B$21/10000*INDEX(Prices!$F$5:$F$25,MATCH("Cool GZRS",Prices!$A$5:$A$25,0))
A13: Cool LRS | B13: =INDEX(Prices!$D$5:$D$25,MATCH("Cool LRS",Prices!$A$5:$A$25,0)) | C13: =Parameters!$B$20*$B13 | D13: =$C13*Parameters!$B$7 | E13: =Parameters!$B$20*Parameters!$B$16+Parameters!$B$21/10000*INDEX(Prices!$E$5:$E$25,MATCH("Cool LRS",Prices!$A$5:$A$25,0)) | F13: =$D13+$E13 | G13: =Parameters!$B$20*INDEX(Prices!$G$5:$G$25,MATCH("Cool LRS",Prices!$A$5:$A$25,0))+Parameters!$B$21/10000*INDEX(Prices!$F$5:$F$25,MATCH("Cool LRS",Prices!$A$5:$A$25,0))
A14: Cool RA-GRS | B14: =INDEX(Prices!$D$5:$D$25,MATCH("Cool RA-GRS",Prices!$A$5:$A$25,0)) | C14: =Parameters!$B$20*$B14 | D14: =$C14*Parameters!$B$7 | E14: =Parameters!$B$20*Parameters!$B$16+Parameters!$B$21/10000*INDEX(Prices!$E$5:$E$25,MATCH("Cool RA-GRS",Prices!$A$5:$A$25,0)) | F14: =$D14+$E14 | G14: =Parameters!$B$20*INDEX(Prices!$G$5:$G$25,MATCH("Cool RA-GRS",Prices!$A$5:$A$25,0))+Parameters!$B$21/10000*INDEX(Prices!$F$5:$F$25,MATCH("Cool RA-GRS",Prices!$A$5:$A$25,0))
A15: Cool RA-GZRS | B15: =INDEX(Prices!$D$5:$D$25,MATCH("Cool RA-GZRS",Prices!$A$5:$A$25,0)) | C15: =Parameters!$B$20*$B15 | D15: =$C15*Parameters!$B$7 | E15: =Parameters!$B$20*Parameters!$B$16+Parameters!$B$21/10000*INDEX(Prices!$E$5:$E$25,MATCH("Cool RA-GZRS",Prices!$A$5:$A$25,0)) | F15: =$D15+$E15 | G15: =Parameters!$B$20*INDEX(Prices!$G$5:$G$25,MATCH("Cool RA-GZRS",Prices!$A$5:$A$25,0))+Parameters!$B$21/10000*INDEX(Prices!$F$5:$F$25,MATCH("Cool RA-GZRS",Prices!$A$5:$A$25,0))
A16: Cool ZRS | B16: =INDEX(Prices!$D$5:$D$25,MATCH("Cool ZRS",Prices!$A$5:$A$25,0)) | C16: =Parameters!$B$20*$B16 | D16: =$C16*Parameters!$B$7 | E16: =Parameters!$B$20*Parameters!$B$16+Parameters!$B$21/10000*INDEX(Prices!$E$5:$E$25,MATCH("Cool ZRS",Prices!$A$5:$A$25,0)) | F16: =$D16+$E16 | G16: =Parameters!$B$20*INDEX(Prices!$G$5:$G$25,MATCH("Cool ZRS",Prices!$A$5:$A$25,0))+Parameters!$B$21/10000*INDEX(Prices!$F$5:$F$25,MATCH("Cool ZRS",Prices!$A$5:$A$25,0))
A17: Cold GRS | B17: =INDEX(Prices!$D$5:$D$25,MATCH("Cold GRS",Prices!$A$5:$A$25,0)) | C17: =Parameters!$B$20*$B17 | D17: =$C17*Parameters!$B$7 | E17: =Parameters!$B$20*Parameters!$B$16+Parameters!$B$21/10000*INDEX(Prices!$E$5:$E$25,MATCH("Cold GRS",Prices!$A$5:$A$25,0)) | F17: =$D17+$E17 | G17: =Parameters!$B$20*INDEX(Prices!$G$5:$G$25,MATCH("Cold GRS",Prices!$A$5:$A$25,0))+Parameters!$B$21/10000*INDEX(Prices!$F$5:$F$25,MATCH("Cold GRS",Prices!$A$5:$A$25,0))
A18: Cold GZRS | B18: =INDEX(Prices!$D$5:$D$25,MATCH("Cold GZRS",Prices!$A$5:$A$25,0)) | C18: =Parameters!$B$20*$B18 | D18: =$C18*Parameters!$B$7 | E18: =Parameters!$B$20*Parameters!$B$16+Parameters!$B$21/10000*INDEX(Prices!$E$5:$E$25,MATCH("Cold GZRS",Prices!$A$5:$A$25,0)) | F18: =$D18+$E18 | G18: =Parameters!$B$20*INDEX(Prices!$G$5:$G$25,MATCH("Cold GZRS",Prices!$A$5:$A$25,0))+Parameters!$B$21/10000*INDEX(Prices!$F$5:$F$25,MATCH("Cold GZRS",Prices!$A$5:$A$25,0))
A19: Cold LRS | B19: =INDEX(Prices!$D$5:$D$25,MATCH("Cold LRS",Prices!$A$5:$A$25,0)) | C19: =Parameters!$B$20*$B19 | D19: =$C19*Parameters!$B$7 | E19: =Parameters!$B$20*Parameters!$B$16+Parameters!$B$21/10000*INDEX(Prices!$E$5:$E$25,MATCH("Cold LRS",Prices!$A$5:$A$25,0)) | F19: =$D19+$E19 | G19: =Parameters!$B$20*INDEX(Prices!$G$5:$G$25,MATCH("Cold LRS",Prices!$A$5:$A$25,0))+Parameters!$B$21/10000*INDEX(Prices!$F$5:$F$25,MATCH("Cold LRS",Prices!$A$5:$A$25,0))
A20: Cold RA-GRS | B20: =INDEX(Prices!$D$5:$D$25,MATCH("Cold RA-GRS",Prices!$A$5:$A$25,0)) | C20: =Parameters!$B$20*$B20 | D20: =$C20*Parameters!$B$7 | E20: =Parameters!$B$20*Parameters!$B$16+Parameters!$B$21/10000*INDEX(Prices!$E$5:$E$25,MATCH("Cold RA-GRS",Prices!$A$5:$A$25,0)) | F20: =$D20+$E20 | G20: =Parameters!$B$20*INDEX(Prices!$G$5:$G$25,MATCH("Cold RA-GRS",Prices!$A$5:$A$25,0))+Parameters!$B$21/10000*INDEX(Prices!$F$5:$F$25,MATCH("Cold RA-GRS",Prices!$A$5:$A$25,0))
A21: Cold RA-GZRS | B21: =INDEX(Prices!$D$5:$D$25,MATCH("Cold RA-GZRS",Prices!$A$5:$A$25,0)) | C21: =Parameters!$B$20*$B21 | D21: =$C21*Parameters!$B$7 | E21: =Parameters!$B$20*Parameters!$B$16+Parameters!$B$21/10000*INDEX(Prices!$E$5:$E$25,MATCH("Cold RA-GZRS",Prices!$A$5:$A$25,0)) | F21: =$D21+$E21 | G21: =Parameters!$B$20*INDEX(Prices!$G$5:$G$25,MATCH("Cold RA-GZRS",Prices!$A$5:$A$25,0))+Parameters!$B$21/10000*INDEX(Prices!$F$5:$F$25,MATCH("Cold RA-GZRS",Prices!$A$5:$A$25,0))
A22: Cold ZRS | B22: =INDEX(Prices!$D$5:$D$25,MATCH("Cold ZRS",Prices!$A$5:$A$25,0)) | C22: =Parameters!$B$20*$B22 | D22: =$C22*Parameters!$B$7 | E22: =Parameters!$B$20*Parameters!$B$16+Parameters!$B$21/10000*INDEX(Prices!$E$5:$E$25,MATCH("Cold ZRS",Prices!$A$5:$A$25,0)) | F22: =$D22+$E22 | G22: =Parameters!$B$20*INDEX(Prices!$G$5:$G$25,MATCH("Cold ZRS",Prices!$A$5:$A$25,0))+Parameters!$B$21/10000*INDEX(Prices!$F$5:$F$25,MATCH("Cold ZRS",Prices!$A$5:$A$25,0))
A23: Archive GRS | B23: =INDEX(Prices!$D$5:$D$25,MATCH("Archive GRS",Prices!$A$5:$A$25,0)) | C23: =Parameters!$B$20*$B23 | D23: =$C23*Parameters!$B$7 | E23: =Parameters!$B$20*Parameters!$B$16+Parameters!$B$21/10000*INDEX(Prices!$E$5:$E$25,MATCH("Archive GRS",Prices!$A$5:$A$25,0)) | F23: =$D23+$E23 | G23: =Parameters!$B$20*INDEX(Prices!$G$5:$G$25,MATCH("Archive GRS",Prices!$A$5:$A$25,0))+Parameters!$B$21/10000*INDEX(Prices!$F$5:$F$25,MATCH("Archive GRS",Prices!$A$5:$A$25,0))
A24: Archive LRS | B24: =INDEX(Prices!$D$5:$D$25,MATCH("Archive LRS",Prices!$A$5:$A$25,0)) | C24: =Parameters!$B$20*$B24 | D24: =$C24*Parameters!$B$7 | E24: =Parameters!$B$20*Parameters!$B$16+Parameters!$B$21/10000*INDEX(Prices!$E$5:$E$25,MATCH("Archive LRS",Prices!$A$5:$A$25,0)) | F24: =$D24+$E24 | G24: =Parameters!$B$20*INDEX(Prices!$G$5:$G$25,MATCH("Archive LRS",Prices!$A$5:$A$25,0))+Parameters!$B$21/10000*INDEX(Prices!$F$5:$F$25,MATCH("Archive LRS",Prices!$A$5:$A$25,0))
A25: Archive RA-GRS | B25: =INDEX(Prices!$D$5:$D$25,MATCH("Archive RA-GRS",Prices!$A$5:$A$25,0)) | C25: =Parameters!$B$20*$B25 | D25: =$C25*Parameters!$B$7 | E25: =Parameters!$B$20*Parameters!$B$16+Parameters!$B$21/10000*INDEX(Prices!$E$5:$E$25,MATCH("Archive RA-GRS",Prices!$A$5:$A$25,0)) | F25: =$D25+$E25 | G25: =Parameters!$B$20*INDEX(Prices!$G$5:$G$25,MATCH("Archive RA-GRS",Prices!$A$5:$A$25,0))+Parameters!$B$21/10000*INDEX(Prices!$F$5:$F$25,MATCH("Archive RA-GRS",Prices!$A$5:$A$25,0))
A27: Archive rows are highlighted: they are almost always the right answer for compliance copies that must exist but will probably never be read. Two caveats. Rehydration takes up to 15 hours at standard priority, and there is a 180-day minimum retention charge, so deleting early still bills you for 180 days.

Sheet Compression sensitivity
A1: How much the answer moves with the compression ratio
A2: Compression is the least certain input and it scales the largest term. Everything else comes from 'Parameters'. Budget with the worst ratio you actually measure, not the average you hope for.
A4: Compression | B4: Artifact GB | C4: Storage over retention | D4: TOTAL | E4: What this looks like in practice
A5: 1 | B5: =Parameters!$B$19/$A5 | C5: =$B5*Parameters!$B$14*Parameters!$B$7 | D5: =$C5+$B5*Parameters!$B$16+ROUNDUP($B5*1024/Parameters!$B$11,0)/10000*Parameters!$B$15 | E5: No compression at all.
A6: 1.02 | B6: =Parameters!$B$19/$A6 | C6: =$B6*Parameters!$B$14*Parameters!$B$7 | D6: =$C6+$B6*Parameters!$B$16+ROUNDUP($B6*1024/Parameters!$B$11,0)/10000*Parameters!$B$15 | E6: Measured worst case: already-compressed or encrypted data.
A7: 1.5 | B7: =Parameters!$B$19/$A7 | C7: =$B7*Parameters!$B$14*Parameters!$B$7 | D7: =$C7+$B7*Parameters!$B$16+ROUNDUP($B7*1024/Parameters!$B$11,0)/10000*Parameters!$B$15 | E7: Pessimistic.
A8: 2 | B8: =Parameters!$B$19/$A8 | C8: =$B8*Parameters!$B$14*Parameters!$B$7 | D8: =$C8+$B8*Parameters!$B$16+ROUNDUP($B8*1024/Parameters!$B$11,0)/10000*Parameters!$B$15 | E8: Conservative planning number.
A9: 3 | B9: =Parameters!$B$19/$A9 | C9: =$B9*Parameters!$B$14*Parameters!$B$7 | D9: =$C9+$B9*Parameters!$B$16+ROUNDUP($B9*1024/Parameters!$B$11,0)/10000*Parameters!$B$15 | E9: Typical native .bak with COMPRESSION.
A10: 4 | B10: =Parameters!$B$19/$A10 | C10: =$B10*Parameters!$B$14*Parameters!$B$7 | D10: =$C10+$B10*Parameters!$B$16+ROUNDUP($B10*1024/Parameters!$B$11,0)/10000*Parameters!$B$15 | E10: Default assumption in the toolkit. Unverified.
A11: 6 | B11: =Parameters!$B$19/$A11 | C11: =$B11*Parameters!$B$14*Parameters!$B$7 | D11: =$C11+$B11*Parameters!$B$16+ROUNDUP($B11*1024/Parameters!$B$11,0)/10000*Parameters!$B$15 | E11: Optimistic; text-heavy schemas.
A12: 10 | B12: =Parameters!$B$19/$A12 | C12: =$B12*Parameters!$B$14*Parameters!$B$7 | D12: =$C12+$B12*Parameters!$B$16+ROUNDUP($B12*1024/Parameters!$B$11,0)/10000*Parameters!$B$15 | E12: Very repetitive data.
A13: 33 | B13: =Parameters!$B$19/$A13 | C13: =$B13*Parameters!$B$14*Parameters!$B$7 | D13: =$C13+$B13*Parameters!$B$16+ROUNDUP($B13*1024/Parameters!$B$11,0)/10000*Parameters!$B$15 | E13: Measured best case: highly repetitive test data. Do not plan on this.
A15: Worst case vs default assumption: | D15: =IFERROR($D6/$D10,0)
A17: Yellow is the toolkit default. Orange is the measured worst case. The gap between them is the single largest source of error in this model.
